goku-0.2.5.data/scripts/goku.py
mypackage/__init__.py
mypackage/goku.py
goku-0.2.5.dist-info/LICENSE
goku-0.2.5.dist-info/METADATA
goku-0.2.5.dist-info/WHEEL
goku-0.2.5.dist-info/top_level.txt
goku-0.2.5.dist-info/RECORD
