Metadata-Version: 2.1
Name: goku
Version: 0.2.5
Summary: A Super Sayaian  package KAAAA__MAEEE--HAA__MAEE_HAAAAAA
Home-page: https://github.com/Jatin543/mypackage2
Author: Jatin Pandey
Author-email: jatinpandeywork@gmail.com
License: UNKNOWN
Platform: UNKNOWN
Classifier: Programming Language :: Python :: 3
Classifier: License :: OSI Approved :: MIT License
Classifier: Operating System :: OS Independent
